{"nodes": [{"id": "users_santy_openclaw_workspace_indicador_sono_sono_score_py", "label": "sono_score.py", "file_type": "code", "source_file": "sono_score.py", "source_location": "L1"}, {"id": "indicador_sono_sono_score_calc_ma", "label": "calc_ma()", "file_type": "code", "source_file": "sono_score.py", "source_location": "L23"}, {"id": "indicador_sono_sono_score_calc_rsi", "label": "calc_rsi()", "file_type": "code", "source_file": "sono_score.py", "source_location": "L28"}, {"id": "indicador_sono_sono_score_calc_bb", "label": "calc_bb()", "file_type": "code", "source_file": "sono_score.py", "source_location": "L38"}, {"id": "indicador_sono_sono_score_calc_atr", "label": "calc_atr()", "file_type": "code", "source_file": "sono_score.py", "source_location": "L46"}, {"id": "indicador_sono_sono_score_calc_adx", "label": "calc_adx()", "file_type": "code", "source_file": "sono_score.py", "source_location": "L62"}, {"id": "indicador_sono_sono_score_compute_score", "label": "compute_score()", "file_type": "code", "source_file": "sono_score.py", "source_location": "L82"}, {"id": "indicador_sono_sono_score_classify_score", "label": "classify_score()", "file_type": "code", "source_file": "sono_score.py", "source_location": "L142"}, {"id": "indicador_sono_sono_score_rationale_1", "label": "sono_score.py \u2014 Score Maestro UNIFICADO (bot Python) Lee umbrales/pesos desde so", "file_type": "rationale", "source_file": "sono_score.py", "source_location": "L1"}, {"id": "indicador_sono_sono_score_rationale_83", "label": "Calcula Score Maestro 0-100.     Misma l\u00f3gica que scoreEngine.js.", "file_type": "rationale", "source_file": "sono_score.py", "source_location": "L83"}, {"id": "indicador_sono_sono_score_rationale_143", "label": "Clasifica total 0-100 usando contrato JSON.", "file_type": "rationale", "source_file": "sono_score.py", "source_location": "L143"}], "edges": [{"source": "users_santy_openclaw_workspace_indicador_sono_sono_score_py", "target": "json", "relation": "imports", "context": "import", "confidence": "EXTRACTED", "source_file": "sono_score.py", "source_location": "L10", "weight": 1.0}, {"source": "users_santy_openclaw_workspace_indicador_sono_sono_score_py", "target": "math", "relation": "imports", "context": "import", "confidence": "EXTRACTED", "source_file": "sono_score.py", "source_location": "L11", "weight": 1.0}, {"source": "users_santy_openclaw_workspace_indicador_sono_sono_score_py", "target": "os", "relation": "imports", "context": "import", "confidence": "EXTRACTED", "source_file": "sono_score.py", "source_location": "L12", "weight": 1.0}, {"source": "users_santy_openclaw_workspace_indicador_sono_sono_score_py", "target": "indicador_sono_sono_score_calc_ma", "relation": "contains", "confidence": "EXTRACTED", "source_file": "sono_score.py", "source_location": "L23", "weight": 1.0}, {"source": "users_santy_openclaw_workspace_indicador_sono_sono_score_py", "target": "indicador_sono_sono_score_calc_rsi", "relation": "contains", "confidence": "EXTRACTED", "source_file": "sono_score.py", "source_location": "L28", "weight": 1.0}, {"source": "users_santy_openclaw_workspace_indicador_sono_sono_score_py", "target": "indicador_sono_sono_score_calc_bb", "relation": "contains", "confidence": "EXTRACTED", "source_file": "sono_score.py", "source_location": "L38", "weight": 1.0}, {"source": "users_santy_openclaw_workspace_indicador_sono_sono_score_py", "target": "indicador_sono_sono_score_calc_atr", "relation": "contains", "confidence": "EXTRACTED", "source_file": "sono_score.py", "source_location": "L46", "weight": 1.0}, {"source": "users_santy_openclaw_workspace_indicador_sono_sono_score_py", "target": "indicador_sono_sono_score_calc_adx", "relation": "contains", "confidence": "EXTRACTED", "source_file": "sono_score.py", "source_location": "L62", "weight": 1.0}, {"source": "users_santy_openclaw_workspace_indicador_sono_sono_score_py", "target": "indicador_sono_sono_score_compute_score", "relation": "contains", "confidence": "EXTRACTED", "source_file": "sono_score.py", "source_location": "L82", "weight": 1.0}, {"source": "users_santy_openclaw_workspace_indicador_sono_sono_score_py", "target": "indicador_sono_sono_score_classify_score", "relation": "contains", "confidence": "EXTRACTED", "source_file": "sono_score.py", "source_location": "L142", "weight": 1.0}, {"source": "users_santy_openclaw_workspace_indicador_sono_sono_score_py", "target": "random", "relation": "imports", "context": "import", "confidence": "EXTRACTED", "source_file": "sono_score.py", "source_location": "L175", "weight": 1.0}, {"source": "indicador_sono_sono_score_compute_score", "target": "indicador_sono_sono_score_calc_ma", "relation": "calls", "context": "call", "confidence": "EXTRACTED", "source_file": "sono_score.py", "source_location": "L91", "weight": 1.0}, {"source": "indicador_sono_sono_score_compute_score", "target": "indicador_sono_sono_score_calc_bb", "relation": "calls", "context": "call", "confidence": "EXTRACTED", "source_file": "sono_score.py", "source_location": "L95", "weight": 1.0}, {"source": "indicador_sono_sono_score_compute_score", "target": "indicador_sono_sono_score_calc_adx", "relation": "calls", "context": "call", "confidence": "EXTRACTED", "source_file": "sono_score.py", "source_location": "L96", "weight": 1.0}, {"source": "indicador_sono_sono_score_compute_score", "target": "indicador_sono_sono_score_calc_rsi", "relation": "calls", "context": "call", "confidence": "EXTRACTED", "source_file": "sono_score.py", "source_location": "L97", "weight": 1.0}, {"source": "indicador_sono_sono_score_compute_score", "target": "indicador_sono_sono_score_calc_atr", "relation": "calls", "context": "call", "confidence": "EXTRACTED", "source_file": "sono_score.py", "source_location": "L98", "weight": 1.0}, {"source": "indicador_sono_sono_score_compute_score", "target": "indicador_sono_sono_score_classify_score", "relation": "calls", "context": "call", "confidence": "EXTRACTED", "source_file": "sono_score.py", "source_location": "L135", "weight": 1.0}, {"source": "indicador_sono_sono_score_rationale_1", "target": "users_santy_openclaw_workspace_indicador_sono_sono_score_py", "relation": "rationale_for", "confidence": "EXTRACTED", "source_file": "sono_score.py", "source_location": "L1", "weight": 1.0}, {"source": "indicador_sono_sono_score_rationale_83", "target": "indicador_sono_sono_score_compute_score", "relation": "rationale_for", "confidence": "EXTRACTED", "source_file": "sono_score.py", "source_location": "L83", "weight": 1.0}, {"source": "indicador_sono_sono_score_rationale_143", "target": "indicador_sono_sono_score_classify_score", "relation": "rationale_for", "confidence": "EXTRACTED", "source_file": "sono_score.py", "source_location": "L143", "weight": 1.0}], "raw_calls": [{"caller_nid": "indicador_sono_sono_score_calc_bb", "callee": "sqrt", "is_member_call": true, "source_file": "/Users/santy/.openclaw/workspace/indicador-sono/sono_score.py", "source_location": "L43"}, {"caller_nid": "indicador_sono_sono_score_calc_atr", "callee": "append", "is_member_call": true, "source_file": "/Users/santy/.openclaw/workspace/indicador-sono/sono_score.py", "source_location": "L59"}, {"caller_nid": "indicador_sono_sono_score_classify_score", "callee": "update", "is_member_call": true, "source_file": "/Users/santy/.openclaw/workspace/indicador-sono/sono_score.py", "source_location": "L168"}]}